tomato/__init__.py
tomato/classes/__init__.py
tomato/classes/agent.py
tomato/classes/board.py
tomato/classes/cell.py
tomato/classes/element.py
tomato/classes/window.py
tomato/functions/__init__.py
tomato/functions/display.py
tomato/functions/file_io.py
tomato/functions/handling_rules.py
tomato/functions/utils.py
tomato/rules/__init__.py
tomato/rules/automata1D.py
tomato/rules/automata1D_demo.py
tomato/rules/cyclic.py
tomato/rules/cyclic_demo.py
tomato/rules/game_of_life.py
tomato/rules/game_of_life_demo.py
tomato/rules/langtons_ant.py
tomato/rules/langtons_ant_demo.py
tomato/rules/random_walkers.py
tomato/rules/random_walkers_demo.py
tomato/rules/tomato_life.py
tomato/rules/tomato_life_demo.py
tomato/rules/toothpick_fractal.py
tomato/rules/toothpick_fractal_demo.py
tomato_engine-2.0.0.dist-info/LICENSE
tomato_engine-2.0.0.dist-info/METADATA
tomato_engine-2.0.0.dist-info/WHEEL
tomato_engine-2.0.0.dist-info/top_level.txt
tomato_engine-2.0.0.dist-info/RECORD
