Metadata-Version: 2.1
Name: tomato-engine
Version: 2.0.0
Summary: Engine for prototyping and playing with cellular automata
Home-page: https://codeberg.org/eduardotogpi/tomato-engine
Author: Eduardo Lopes Dias, Murilo Melhem
Author-email: eduardosprp@usp.br
Project-URL: Bug Tracker, https://codeberg.org/eduardotogpi/tomato-engine/issues
Classifier: Programming Language :: Python :: 3
Classifier: License :: OSI Approved :: GNU General Public License v3 or later (GPLv3+)
Classifier: Operating System :: OS Independent
Requires-Python: >=3.9
License-File: LICENSE
Requires-Dist: numpy
Requires-Dist: pygame
Requires-Dist: pillow
Requires-Dist: ipython
Provides-Extra: rulesets
Requires-Dist: tomato-rules ; extra == 'rulesets'
